<?xml version="1.0" encoding="UTF-8"?>
<GateDocument>
<!-- The document's features-->

<GateDocumentFeatures>
</GateDocumentFeatures>
<!-- The document content area with serialized nodes -->

<TextWithNodes><Node id="0"/>  Институт автоматики и процессов управления гетеросистема, гомоэпитаксия, наноэлектроника, оптоэлектроника   Физика твердого тела Физическая электроника   Изучение процессов роста легированных и нелегированных пленок кремния и формирования многослойных гетеросистем в условиях сверхвысокого вакуума развитие метода молекулярно-лучевой эпитаксии кремния для получения новых объектов и материалов для физических исследований и создания эпитаксиальных полупроводниковых структур для элементов микро-, нано-, и оптоэлектроники                          Балашев Вячеслав Владимирович, научный сотрудник, кандидат наук Викулов Виктор А., научный сотрудник, кандидат наук Коробцов Владимир Викторович, заведующий лабороторией, доктор наук <Node id="732"/>Писаренко<Node id="741"/> <Node id="742"/>Татьяна А.<Node id="752"/>, научный сотрудник Состав лаборатории: 
 
Количество сотрудников - 4, 
научных сотрудников - 4, 
докторов наук - 1, 
кандидатов наук - 2 
 
 
 
Основные результаты 
 
Изучена динамика процессов взаимодействия потока В2О3 с Si(111) и Si(100) поверхностями: определены лимитирующая стадия и кинетические характеристики разложения В2О3. 
 
Обнаружен эффект селективной адсорбции газовых компонент из атмосферы воздуха на модифицированной бором поверхности кремния с ориентацией (111) и изучена возможность его применения для синтеза островков нитрида бора на поверхности кремния.   2 Сверхвысоковакуумные установки LAS-600 фирмы "RIBER", оснащенные различным аналитическим оборудованием 3 отечественные сверхвысоковакуумные установки собственного изготовления, оснащенные различными наборами аналитического оборудования для исследования оптических спектров отражения и пропускания Сверхвысоковакуумная исследовательско-технологическая установка молекулярно-лучевой эпитаксии "Катунь" отечественного производства для исследования молекулярно-лучевой и твердофазной эпитаксии кремния Сверхвысоковакуумная установка DEL-300 фирмы "RIBER" Сверхвысоковакуумная установка фирмы VARIAN, оснащенная методами электронной ожэ-спектроскопии и рентгеновской фотоэлектронной спектроскопии, ионной пушкой, манипулятором, блоком испарителей, оптическими вводами Сканирующий туннельный микроскоп VT-<Node id="2133"/>STM<Node id="2136"/> фирмы "Омикрон" Сканирующий туннельный микроскоп фирмы "Омикрон" Управляемая компьютером установка для исследования фотоспектральных характеристик гетероструктур в диапазоне длин волн 0.4 - 2.2 мкм Установки для исследования температурных зависимостей термо-эдс и эдс Холла и вольтамперных характеристик гетероструктур Фемтосекундный лазер для исследования поверхности   Автоматические двухлучевые спектрофотометры "SPECORD" для работы в диапазоне длин волн 0.2 - 15 мкм Контрольно-измерительная аппаратура   Инженерный факультет университета г. Осака, Япония Институт физики полупроводников, Франкфурт-на-Одере, Германия Институт физики твердого тела, Ганновер, Германия Институт электроники университета г. Шизуока, Хамаматсу,  Япония Университет Бундесвера, Институт физики, Мюнхен, Германия Университет г. Беер-Шева, Израиль Факультет квантовой инженерии Нагойского университета, Япония Физико-химический институт, Университет г. Хейдельберг, Германия      </TextWithNodes>
<!-- The default annotation set -->

<AnnotationSet>
</AnnotationSet>

<!-- Named annotation set -->

<AnnotationSet Name="Key">
<Annotation Id="0" Type="связи_с_другими_организациями" StartNode="0" EndNode="0">
</Annotation>
<Annotation Id="1" Type="связанные_организации" StartNode="0" EndNode="0">
</Annotation>
<Annotation Id="2" Type="связи_с_организациями" StartNode="0" EndNode="0">
</Annotation>
<Annotation Id="3" Type="связи_с_персонами" StartNode="0" EndNode="0">
</Annotation>
<Annotation Id="4" Type="связи_с_другими_организациями" StartNode="0" EndNode="0">
</Annotation>
<Annotation Id="5" Type="связи_с_другими_организациями" StartNode="0" EndNode="0">
</Annotation>
<Annotation Id="6" Type="связи_с_персонами" StartNode="0" EndNode="0">
</Annotation>
<Annotation Id="7" Type="связи_с_другими_организациями" StartNode="0" EndNode="0">
</Annotation>
<Annotation Id="8" Type="связи_с_другими_организациями" StartNode="0" EndNode="0">
</Annotation>
<Annotation Id="9" Type="Персона" StartNode="742" EndNode="752">
<Feature>
  <Name className="java.lang.String">Инициал</Name>
  <Value className="java.lang.String">А.</Value>
</Feature>
<Feature>
  <Name className="java.lang.String">связи_с_организациями</Name>
  <Value className="java.lang.String">null</Value>
</Feature>
<Feature>
  <Name className="java.lang.String">Фамилия</Name>
  <Value className="java.lang.String">Татьян</Value>
</Feature>
</Annotation>
<Annotation Id="10" Type="связи_с_персонами" StartNode="0" EndNode="0">
</Annotation>
<Annotation Id="11" Type="Сканирующая+туннельная+микроскопия" StartNode="2133" EndNode="2136">
<Feature>
  <Name className="java.lang.String">связанные_организации</Name>
  <Value className="java.lang.String">null</Value>
</Feature>
</Annotation>
<Annotation Id="12" Type="связи_с_персонами" StartNode="0" EndNode="0">
</Annotation>
<Annotation Id="13" Type="Персона" StartNode="732" EndNode="741">
<Feature>
  <Name className="java.lang.String">связи_с_организациями</Name>
  <Value className="java.lang.String">null</Value>
</Feature>
<Feature>
  <Name className="java.lang.String">Фамилия</Name>
  <Value className="java.lang.String">Писаренко</Value>
</Feature>
</Annotation>
<Annotation Id="14" Type="связи_с_организациями" StartNode="0" EndNode="0">
</Annotation>
<Annotation Id="15" Type="связи_с_организациями" StartNode="0" EndNode="0">
</Annotation>
<Annotation Id="17" Type="связи_с_другими_организациями" StartNode="0" EndNode="0">
</Annotation>
<Annotation Id="16" Type="связи_с_другими_организациями" StartNode="0" EndNode="0">
</Annotation>
<Annotation Id="19" Type="связанные_термины" StartNode="0" EndNode="0">
</Annotation>
<Annotation Id="18" Type="связи_с_организациями" StartNode="0" EndNode="0">
</Annotation>
<Annotation Id="21" Type="связи_с_другими_организациями" StartNode="0" EndNode="0">
</Annotation>
<Annotation Id="20" Type="связи_с_другими_организациями" StartNode="0" EndNode="0">
</Annotation>
<Annotation Id="23" Type="связи_с_другими_организациями" StartNode="0" EndNode="0">
</Annotation>
<Annotation Id="22" Type="связи_с_персонами" StartNode="0" EndNode="0">
</Annotation>
<Annotation Id="25" Type="связи_с_другими_организациями" StartNode="0" EndNode="0">
</Annotation>
<Annotation Id="24" Type="связи_с_организациями" StartNode="0" EndNode="0">
</Annotation>
<Annotation Id="27" Type="связи_с_другими_организациями" StartNode="0" EndNode="0">
</Annotation>
<Annotation Id="26" Type="связи_с_другими_организациями" StartNode="0" EndNode="0">
</Annotation>
</AnnotationSet>

</GateDocument>
